yawsso/__init__.py
yawsso/__main__.py
yawsso/cli.py
yawsso/cmd.py
yawsso/core.py
yawsso/utils.py
yawsso-1.2.1.dist-info/LICENSE
yawsso-1.2.1.dist-info/METADATA
yawsso-1.2.1.dist-info/WHEEL
yawsso-1.2.1.dist-info/entry_points.txt
yawsso-1.2.1.dist-info/top_level.txt
yawsso-1.2.1.dist-info/RECORD
