Metadata-Version: 2.1
Name: yawsso
Version: 1.2.1
Summary: Yet Another AWS SSO - sync up AWS CLI v2 SSO login session to legacy CLI v1 credentials
Home-page: https://github.com/victorskl/yawsso
Author: Victor San Kho Lin
Author-email: victor@sankholin.com
License: MIT
Project-URL: Bug Tracker, https://github.com/victorskl/yawsso/issues
Classifier: Development Status :: 5 - Production/Stable
Classifier: Programming Language :: Python :: 3
Classifier: License :: OSI Approved :: MIT License
Classifier: Operating System :: OS Independent
Requires-Python: >=3.7
License-File: LICENSE
Provides-Extra: all
Requires-Dist: pyperclip; extra == "all"
Provides-Extra: dev
Requires-Dist: twine; extra == "dev"
Requires-Dist: setuptools; extra == "dev"
Requires-Dist: wheel; extra == "dev"
Requires-Dist: build; extra == "dev"
Requires-Dist: aws-cdk-lib; extra == "dev"
Requires-Dist: constructs; extra == "dev"
Requires-Dist: tox; extra == "dev"
Requires-Dist: nose2; extra == "dev"
Requires-Dist: pre-commit; extra == "dev"
Requires-Dist: detect-secrets; extra == "dev"
Requires-Dist: ggshield; extra == "dev"
Provides-Extra: test
Requires-Dist: pytest; extra == "test"
Requires-Dist: pytest-cov; extra == "test"
Requires-Dist: flake8; extra == "test"
Requires-Dist: mockito; extra == "test"
Requires-Dist: cli-test-helpers; extra == "test"
Requires-Dist: coveralls; extra == "test"
Requires-Dist: pyperclip; extra == "test"
